darling/__init__.py
darling/_color.py
darling/_dataset.py
darling/assets.py
darling/goniometer.py
darling/metadata.py
darling/peaksearcher.py
darling/properties.py
darling/reader.py
darling/transforms.py
darling/assets/example_data/domains/2D_domains.h5
darling/assets/example_data/misc/mosa_Al_1050_stregnthening_pct5_large_range.npy
darling/assets/example_data/mosa_scan_id03/mosa_scan.h5
darling/assets/example_data/motor_drift/motor_drift.h5
darling/assets/example_data/rocking_scan_id03/rocking.h5
darling/assets/saves/energy_stack.h5
darling/assets/saves/energy_stack.xdmf
darling/assets/saves/mosa_stack.h5
darling/assets/saves/mosa_stack.xdmf
darling_pypi-1.0.0.dist-info/METADATA
darling_pypi-1.0.0.dist-info/WHEEL
darling_pypi-1.0.0.dist-info/licenses/LICENSE
darling_pypi-1.0.0.dist-info/RECORD
