Metadata-Version: 2.4
Name: darling-pypi
Version: 1.0.0
Summary: A python [D]ark field x-ray microscopy [A]nalysis &amp; [R]econstruction [L]ibrary for rapid data [IN]spection &amp; [G]raphing
Project-URL: Homepage, https://axelhenningsson.github.io/darling/
Project-URL: Repository, https://github.com/axelhenningsson/darling
Project-URL: Issues, https://github.com/axelhenningsson/darling/issues
Author-email: Axel Henningsson <nilsaxelhenningsson@gmail.com>
License: MIT License
License-File: LICENSE
Keywords: crystallography,dfxm,materials-science,microscopy,x-ray
Classifier: Development Status :: 3 - Alpha
Classifier: Intended Audience :: Science/Research
Classifier: License :: OSI Approved :: MIT License
Classifier: Programming Language :: Python :: 3
Classifier: Programming Language :: Python :: 3.9
Classifier: Programming Language :: Python :: 3.10
Classifier: Programming Language :: Python :: 3.11
Requires-Python: >=3.9
Requires-Dist: h5py
Requires-Dist: hdf5plugin
Requires-Dist: matplotlib
Requires-Dist: meshio
Requires-Dist: numba
Requires-Dist: numpy
Requires-Dist: scipy
